simplebot_encryption_error.py
simplebot_encryption_error-1.0.0.dist-info/LICENSE
simplebot_encryption_error-1.0.0.dist-info/METADATA
simplebot_encryption_error-1.0.0.dist-info/WHEEL
simplebot_encryption_error-1.0.0.dist-info/entry_points.txt
simplebot_encryption_error-1.0.0.dist-info/top_level.txt
simplebot_encryption_error-1.0.0.dist-info/RECORD
